fastapi_doc_http_response/__init__.py
fastapi_doc_http_response/http_responses.py
tests/__init__.py
tests/test_http_response.py
fastapi_doc_http_response-0.0.3.dist-info/LICENSE
fastapi_doc_http_response-0.0.3.dist-info/METADATA
fastapi_doc_http_response-0.0.3.dist-info/WHEEL
fastapi_doc_http_response-0.0.3.dist-info/top_level.txt
fastapi_doc_http_response-0.0.3.dist-info/RECORD
