Metadata-Version: 2.1
Name: fastapi-doc-http-response
Version: 0.0.3
Summary: This is a Python package that simplifies the definition of standard HTTP responses for FastAPI APIs.
Home-page: https://github.com/tharlesamaro/fastapi-doc-http-response
Author: Tharles Amaro
Author-email: tharlesamaro@gmail.com
License: MIT
Keywords: fastapi,http,response,api,documentation
Classifier: Development Status :: 4 - Beta
Classifier: Environment :: Web Environment
Classifier: License :: OSI Approved :: MIT License
Classifier: Topic :: Internet
Classifier: Topic :: Internet :: WWW/HTTP :: HTTP Servers
Classifier: Topic :: Internet :: WWW/HTTP
Classifier: Topic :: Software Development :: Libraries :: Application Frameworks
Classifier: Topic :: Software Development :: Libraries :: Python Modules
Classifier: Topic :: Software Development :: Libraries
Classifier: Topic :: Software Development :: Code Generators
Classifier: Topic :: Software Development
Classifier: Typing :: Typed
Classifier: Operating System :: OS Independent
Classifier: Programming Language :: Python :: 3
Classifier: Programming Language :: Python :: 3 :: Only
Classifier: Programming Language :: Python :: 3.10
Classifier: Programming Language :: Python :: 3.11
Classifier: Programming Language :: Python
Requires-Python: >=3.10
License-File: LICENSE
Requires-Dist: fastapi
